AUTHORS.rst
CONTRIBUTING.rst
HISTORY.rst
LICENSE
MANIFEST.in
README.rst
setup.cfg
setup.py
chop/__init__.py
chop/chop.py
chop/cli.py
chop3.egg-info/PKG-INFO
chop3.egg-info/SOURCES.txt
chop3.egg-info/dependency_links.txt
chop3.egg-info/entry_points.txt
chop3.egg-info/not-zip-safe
chop3.egg-info/requires.txt
chop3.egg-info/top_level.txt
docs/Makefile
docs/authors.rst
docs/conf.py
docs/contributing.rst
docs/history.rst
docs/index.rst
docs/installation.rst
docs/make.bat
docs/readme.rst
docs/usage.rst
tests/test_chop.py