Metadata-Version: 1.1
Name: chop3
Version: 0.1.0
Summary: Produce the time distance diagram for different chooper configuration
Home-page: https://github.com/ornlneutronimaging/chop
Author: Fahima Islam
Author-email: ffiqnf.2017@gmail.com
License: MIT license
Download-URL: https://github.com/ornlneutronimaging/chop/archive/v0.1.0.tar.gz
Keywords: chop
Platform: UNKNOWN
Classifier: Development Status :: 2 - Pre-Alpha
Classifier: Intended Audience :: Developers
Classifier: License :: OSI Approved :: MIT License
Classifier: Natural Language :: English
Classifier: Programming Language :: Python :: 2
Classifier: Programming Language :: Python :: 2.7
Classifier: Programming Language :: Python :: 3
Classifier: Programming Language :: Python :: 3.4
Classifier: Programming Language :: Python :: 3.5
Classifier: Programming Language :: Python :: 3.6
Classifier: Programming Language :: Python :: 3.7
